{
  "active_alarms": [
    {
      "id": "alarm_1765103558_18",
      "threat_level": "CRITICAL",
      "vehicle_type": "2S1",
      "confidence": 0.9943267703056335,
      "threat_score": 0.9446104317903519,
      "timestamp": "2025-12-07T16:02:38.912776",
      "image_data": null,
      "acknowledged": false,
      "message": "CRITICAL threat detected: 2S1"
    },
    {
      "id": "alarm_1765179538_19",
      "threat_level": "HIGH",
      "vehicle_type": "BMP2",
      "confidence": 0.9981315732002258,
      "threat_score": 0.8355515775680543,
      "timestamp": "2025-12-08T13:08:58.935587",
      "image_data": null,
      "acknowledged": false,
      "message": "HIGH threat detected: BMP2",
      "sar_validated": true
    },
    {
      "id": "alarm_1765179969_20",
      "threat_level": "CRITICAL",
      "vehicle_type": "T62",
      "confidence": 0.9999722242355347,
      "threat_score": 0.9927420839071275,
      "timestamp": "2025-12-08T13:16:09.166006",
      "image_data": null,
      "acknowledged": false,
      "message": "CRITICAL threat detected: T62",
      "sar_validated": true
    },
    {
      "id": "alarm_1765180041_21",
      "threat_level": "CRITICAL",
      "vehicle_type": "T72",
      "confidence": 0.9999910593032837,
      "threat_score": 0.9927474519014358,
      "timestamp": "2025-12-08T13:17:21.743200",
      "image_data": null,
      "acknowledged": false,
      "message": "CRITICAL threat detected: T72",
      "sar_validated": true
    },
    {
      "id": "alarm_1765182973_22",
      "threat_level": "CRITICAL",
      "vehicle_type": "T62",
      "confidence": 0.9998051524162292,
      "threat_score": 0.9926944684386253,
      "timestamp": "2025-12-08T14:06:13.630934",
      "image_data": null,
      "acknowledged": false,
      "message": "CRITICAL threat detected: T62",
      "sar_validated": true
    },
    {
      "id": "alarm_1765182996_23",
      "threat_level": "HIGH",
      "vehicle_type": "2S1",
      "confidence": 0.9996274709701538,
      "threat_score": 0.8359105930328369,
      "timestamp": "2025-12-08T14:06:36.763547",
      "image_data": null,
      "acknowledged": false,
      "message": "HIGH threat detected: 2S1",
      "sar_validated": true
    },
    {
      "id": "alarm_1765195107_24",
      "threat_level": "CRITICAL",
      "vehicle_type": "T72",
      "confidence": 0.9999982118606567,
      "threat_score": 0.992749490380287,
      "timestamp": "2025-12-08T17:28:27.521851",
      "image_data": null,
      "acknowledged": false,
      "message": "CRITICAL threat detected: T72",
      "sar_validated": true
    },
    {
      "id": "alarm_1765195205_25",
      "threat_level": "CRITICAL",
      "vehicle_type": "T72",
      "confidence": 0.9978808164596558,
      "threat_score": 0.9921460326910018,
      "timestamp": "2025-12-08T17:30:05.989103",
      "image_data": null,
      "acknowledged": false,
      "message": "CRITICAL threat detected: T72",
      "sar_validated": true
    },
    {
      "id": "alarm_1765205557_26",
      "threat_level": "HIGH",
      "vehicle_type": "BMP2",
      "confidence": 0.9981619715690613,
      "threat_score": 0.8355588731765748,
      "timestamp": "2025-12-08T20:22:37.789338",
      "image_data": null,
      "acknowledged": false,
      "message": "HIGH threat detected: BMP2",
      "sar_validated": true
    },
    {
      "id": "alarm_1765205660_27",
      "threat_level": "HIGH",
      "vehicle_type": "BMP2",
      "confidence": 0.9997324347496033,
      "threat_score": 0.8359357843399048,
      "timestamp": "2025-12-08T20:24:20.810754",
      "image_data": null,
      "acknowledged": false,
      "message": "HIGH threat detected: BMP2",
      "sar_validated": true
    },
    {
      "id": "alarm_1765206488_28",
      "threat_level": "HIGH",
      "vehicle_type": "ZSU_23_4",
      "confidence": 0.9999785423278809,
      "threat_score": 0.8359948501586913,
      "timestamp": "2025-12-08T20:38:08.584252",
      "image_data": null,
      "acknowledged": false,
      "message": "HIGH threat detected: ZSU_23_4",
      "sar_validated": true
    },
    {
      "id": "alarm_1765208515_29",
      "threat_level": "HIGH",
      "vehicle_type": "ZSU_23_4",
      "confidence": 0.9998701810836792,
      "threat_score": 0.835968843460083,
      "timestamp": "2025-12-08T21:11:55.549486",
      "image_data": null,
      "acknowledged": false,
      "message": "HIGH threat detected: ZSU_23_4",
      "sar_validated": true
    },
    {
      "id": "alarm_1765208535_30",
      "threat_level": "CRITICAL",
      "vehicle_type": "T72",
      "confidence": 0.9999910593032837,
      "threat_score": 0.9927474519014358,
      "timestamp": "2025-12-08T21:12:15.154767",
      "image_data": null,
      "acknowledged": false,
      "message": "CRITICAL threat detected: T72",
      "sar_validated": true
    },
    {
      "id": "alarm_1765208557_31",
      "threat_level": "HIGH",
      "vehicle_type": "2S1",
      "confidence": 0.9970923662185669,
      "threat_score": 0.8353021678924561,
      "timestamp": "2025-12-08T21:12:37.365905",
      "image_data": null,
      "acknowledged": false,
      "message": "HIGH threat detected: 2S1",
      "sar_validated": true
    },
    {
      "id": "alarm_1765263847_32",
      "threat_level": "HIGH",
      "vehicle_type": "2S1",
      "confidence": 0.9970923662185669,
      "threat_score": 0.8353021678924561,
      "timestamp": "2025-12-09T12:34:07.505324",
      "image_data": null,
      "acknowledged": false,
      "message": "HIGH threat detected: 2S1",
      "sar_validated": true
    },
    {
      "id": "alarm_1765285754_33",
      "threat_level": "HIGH",
      "vehicle_type": "2S1",
      "confidence": 0.9970923662185669,
      "threat_score": 0.8353021678924561,
      "timestamp": "2025-12-09T18:39:14.874440",
      "image_data": null,
      "acknowledged": false,
      "message": "HIGH threat detected: 2S1",
      "sar_validated": true
    },
    {
      "id": "alarm_1765285778_34",
      "threat_level": "CRITICAL",
      "vehicle_type": "T62",
      "confidence": 0.998097836971283,
      "threat_score": 0.9922078835368157,
      "timestamp": "2025-12-09T18:39:38.751802",
      "image_data": null,
      "acknowledged": false,
      "message": "CRITICAL threat detected: T62",
      "sar_validated": true
    },
    {
      "id": "alarm_1765287383_35",
      "threat_level": "CRITICAL",
      "vehicle_type": "T62",
      "confidence": 0.9994402527809143,
      "threat_score": 0.9925904720425607,
      "timestamp": "2025-12-09T19:06:23.897856",
      "image_data": null,
      "acknowledged": false,
      "message": "CRITICAL threat detected: T62",
      "sar_validated": true
    },
    {
      "id": "alarm_1765287404_36",
      "threat_level": "HIGH",
      "vehicle_type": "2S1",
      "confidence": 0.9998249411582947,
      "threat_score": 0.8359579858779909,
      "timestamp": "2025-12-09T19:06:44.934951",
      "image_data": null,
      "acknowledged": false,
      "message": "HIGH threat detected: 2S1",
      "sar_validated": true
    },
    {
      "id": "alarm_1765288370_37",
      "threat_level": "HIGH",
      "vehicle_type": "2S1",
      "confidence": 0.9970923662185669,
      "threat_score": 0.8353021678924561,
      "timestamp": "2025-12-09T19:22:50.476309",
      "image_data": null,
      "acknowledged": false,
      "message": "HIGH threat detected: 2S1",
      "sar_validated": true
    },
    {
      "id": "alarm_1765288389_38",
      "threat_level": "HIGH",
      "vehicle_type": "2S1",
      "confidence": 0.9970923662185669,
      "threat_score": 0.8353021678924561,
      "timestamp": "2025-12-09T19:23:09.617210",
      "image_data": null,
      "acknowledged": false,
      "message": "HIGH threat detected: 2S1",
      "sar_validated": true
    },
    {
      "id": "alarm_1765288554_39",
      "threat_level": "HIGH",
      "vehicle_type": "2S1",
      "confidence": 0.9970923662185669,
      "threat_score": 0.8353021678924561,
      "timestamp": "2025-12-09T19:25:54.295995",
      "image_data": null,
      "acknowledged": false,
      "message": "HIGH threat detected: 2S1",
      "sar_validated": true
    },
    {
      "id": "alarm_1765339287_40",
      "threat_level": "CRITICAL",
      "vehicle_type": "T62",
      "confidence": 0.9997790455818176,
      "threat_score": 0.992687027990818,
      "timestamp": "2025-12-10T09:31:27.071530",
      "image_data": null,
      "acknowledged": false,
      "message": "CRITICAL threat detected: T62",
      "sar_validated": true
    },
    {
      "id": "alarm_1765339642_41",
      "threat_level": "HIGH",
      "vehicle_type": "BMP2",
      "confidence": 0.9416980147361755,
      "threat_score": 0.8220075235366822,
      "timestamp": "2025-12-10T09:37:22.971361",
      "image_data": null,
      "acknowledged": false,
      "message": "HIGH threat detected: BMP2",
      "sar_validated": true
    },
    {
      "id": "alarm_1765340037_42",
      "threat_level": "CRITICAL",
      "vehicle_type": "T62",
      "confidence": 0.9997790455818176,
      "threat_score": 0.992687027990818,
      "timestamp": "2025-12-10T09:43:57.805166",
      "image_data": null,
      "acknowledged": false,
      "message": "CRITICAL threat detected: T62",
      "sar_validated": true
    },
    {
      "id": "alarm_1765340852_43",
      "threat_level": "HIGH",
      "vehicle_type": "BMP2",
      "confidence": 0.9959074258804321,
      "threat_score": 0.8350177822113038,
      "timestamp": "2025-12-10T09:57:32.814156",
      "image_data": null,
      "acknowledged": false,
      "message": "HIGH threat detected: BMP2",
      "sar_validated": true
    },
    {
      "id": "alarm_1765340894_44",
      "threat_level": "CRITICAL",
      "vehicle_type": "T62",
      "confidence": 0.9999992847442627,
      "threat_score": 0.9927497961521149,
      "timestamp": "2025-12-10T09:58:14.588937",
      "image_data": null,
      "acknowledged": false,
      "message": "CRITICAL threat detected: T62",
      "sar_validated": true
    },
    {
      "id": "alarm_1765341878_45",
      "threat_level": "CRITICAL",
      "vehicle_type": "T72",
      "confidence": 0.9855168461799622,
      "threat_score": 0.9886223011612892,
      "timestamp": "2025-12-10T10:14:38.404883",
      "image_data": null,
      "acknowledged": false,
      "message": "CRITICAL threat detected: T72",
      "sar_validated": true
    },
    {
      "id": "alarm_1765345538_46",
      "threat_level": "CRITICAL",
      "vehicle_type": "T62",
      "confidence": 0.9999767541885376,
      "threat_score": 0.9927433749437331,
      "timestamp": "2025-12-10T11:15:38.961311",
      "image_data": null,
      "acknowledged": false,
      "message": "CRITICAL threat detected: T62",
      "sar_validated": true
    },
    {
      "id": "alarm_1765346843_47",
      "threat_level": "CRITICAL",
      "vehicle_type": "T72",
      "confidence": 0.9855168461799622,
      "threat_score": 0.9886223011612892,
      "timestamp": "2025-12-10T11:37:23.875880",
      "image_data": null,
      "acknowledged": false,
      "message": "CRITICAL threat detected: T72",
      "sar_validated": true
    },
    {
      "id": "alarm_1765347810_48",
      "threat_level": "CRITICAL",
      "vehicle_type": "T62",
      "confidence": 0.9999992847442627,
      "threat_score": 0.9927497961521149,
      "timestamp": "2025-12-10T11:53:30.544161",
      "image_data": null,
      "acknowledged": false,
      "message": "CRITICAL threat detected: T62",
      "sar_validated": true
    },
    {
      "id": "alarm_1765347898_49",
      "threat_level": "CRITICAL",
      "vehicle_type": "T62",
      "confidence": 0.9999992847442627,
      "threat_score": 0.9927497961521149,
      "timestamp": "2025-12-10T11:54:58.200921",
      "image_data": null,
      "acknowledged": false,
      "message": "CRITICAL threat detected: T62",
      "sar_validated": true
    },
    {
      "id": "alarm_1765348061_50",
      "threat_level": "CRITICAL",
      "vehicle_type": "T62",
      "confidence": 0.9999151229858398,
      "threat_score": 0.9927258100509643,
      "timestamp": "2025-12-10T11:57:41.468359",
      "image_data": null,
      "acknowledged": false,
      "message": "CRITICAL threat detected: T62",
      "sar_validated": true
    },
    {
      "id": "alarm_1765348300_50",
      "threat_level": "CRITICAL",
      "vehicle_type": "T62",
      "confidence": 0.9999992847442627,
      "threat_score": 0.9927497961521149,
      "timestamp": "2025-12-10T12:01:40.926117",
      "image_data": null,
      "acknowledged": false,
      "message": "CRITICAL threat detected: T62",
      "sar_validated": true
    },
    {
      "id": "alarm_1765348458_50",
      "threat_level": "CRITICAL",
      "vehicle_type": "T62",
      "confidence": 0.9999151229858398,
      "threat_score": 0.9927258100509643,
      "timestamp": "2025-12-10T12:04:18.036912",
      "image_data": null,
      "acknowledged": false,
      "message": "CRITICAL threat detected: T62",
      "sar_validated": true
    },
    {
      "id": "alarm_1765349496_50",
      "threat_level": "CRITICAL",
      "vehicle_type": "T62",
      "confidence": 0.9994136095046997,
      "threat_score": 0.9925828787088394,
      "timestamp": "2025-12-10T12:21:36.670358",
      "image_data": null,
      "acknowledged": false,
      "message": "CRITICAL threat detected: T62",
      "sar_validated": true
    },
    {
      "id": "alarm_1765350975_50",
      "threat_level": "CRITICAL",
      "vehicle_type": "T62",
      "confidence": 0.9999151229858398,
      "threat_score": 0.9927258100509643,
      "timestamp": "2025-12-10T12:46:15.130478",
      "image_data": null,
      "acknowledged": false,
      "message": "CRITICAL threat detected: T62",
      "sar_validated": true
    },
    {
      "id": "alarm_1765357716_50",
      "threat_level": "CRITICAL",
      "vehicle_type": "T62",
      "confidence": 0.9999992847442627,
      "threat_score": 0.9927497961521149,
      "timestamp": "2025-12-10T14:38:36.079320",
      "image_data": null,
      "acknowledged": false,
      "message": "CRITICAL threat detected: T62",
      "sar_validated": true
    },
    {
      "id": "alarm_1765357830_50",
      "threat_level": "HIGH",
      "vehicle_type": "2S1",
      "confidence": 0.9995386600494385,
      "threat_score": 0.8358892784118652,
      "timestamp": "2025-12-10T14:40:30.252075",
      "image_data": null,
      "acknowledged": false,
      "message": "HIGH threat detected: 2S1",
      "sar_validated": true
    },
    {
      "id": "alarm_1765434307_50",
      "threat_level": "HIGH",
      "vehicle_type": "2S1",
      "confidence": 0.9965943694114685,
      "threat_score": 0.8351826486587526,
      "timestamp": "2025-12-11T11:55:07.997353",
      "image_data": null,
      "acknowledged": false,
      "message": "HIGH threat detected: 2S1",
      "sar_validated": true
    },
    {
      "id": "alarm_1765434330_50",
      "threat_level": "CRITICAL",
      "vehicle_type": "T62",
      "confidence": 0.999998927116394,
      "threat_score": 0.9927496942281723,
      "timestamp": "2025-12-11T11:55:30.180148",
      "image_data": null,
      "acknowledged": false,
      "message": "CRITICAL threat detected: T62",
      "sar_validated": true
    },
    {
      "id": "alarm_1765434521_50",
      "threat_level": "CRITICAL",
      "vehicle_type": "T62",
      "confidence": 0.999998927116394,
      "threat_score": 0.9927496942281723,
      "timestamp": "2025-12-11T11:58:41.749334",
      "image_data": null,
      "acknowledged": false,
      "message": "CRITICAL threat detected: T62",
      "sar_validated": true
    },
    {
      "id": "alarm_1765468527_50",
      "threat_level": "CRITICAL",
      "vehicle_type": "T62",
      "confidence": 0.9999151229858398,
      "threat_score": 0.9927258100509643,
      "timestamp": "2025-12-11T21:25:27.485671",
      "image_data": null,
      "acknowledged": false,
      "message": "CRITICAL threat detected: T62",
      "sar_validated": true
    },
    {
      "id": "alarm_1767150869_50",
      "threat_level": "CRITICAL",
      "vehicle_type": "T62",
      "confidence": 0.9999992847442627,
      "threat_score": 0.9927497961521149,
      "timestamp": "2025-12-31T08:44:29.536619",
      "image_data": null,
      "acknowledged": false,
      "message": "CRITICAL threat detected: T62",
      "sar_validated": true
    },
    {
      "id": "alarm_1767151012_50",
      "threat_level": "CRITICAL",
      "vehicle_type": "T62",
      "confidence": 0.999998927116394,
      "threat_score": 0.9927496942281723,
      "timestamp": "2025-12-31T08:46:52.043114",
      "image_data": null,
      "acknowledged": false,
      "message": "CRITICAL threat detected: T62",
      "sar_validated": true
    },
    {
      "id": "alarm_1767434582_50",
      "threat_level": "CRITICAL",
      "vehicle_type": "T62",
      "confidence": 0.9999151229858398,
      "threat_score": 0.9927258100509643,
      "timestamp": "2026-01-03T15:33:02.988362",
      "image_data": null,
      "acknowledged": false,
      "message": "CRITICAL threat detected: T62",
      "sar_validated": true
    },
    {
      "id": "alarm_1767863547_50",
      "threat_level": "CRITICAL",
      "vehicle_type": "T62",
      "confidence": 0.9999992847442627,
      "threat_score": 0.9927497961521149,
      "timestamp": "2026-01-08T14:42:27.734685",
      "image_data": null,
      "acknowledged": false,
      "message": "CRITICAL threat detected: T62",
      "sar_validated": true
    },
    {
      "id": "alarm_1767931518_50",
      "threat_level": "CRITICAL",
      "vehicle_type": "T62",
      "confidence": 0.999998927116394,
      "threat_score": 0.9927496942281723,
      "timestamp": "2026-01-09T09:35:18.552258",
      "image_data": null,
      "acknowledged": false,
      "message": "CRITICAL threat detected: T62",
      "sar_validated": true
    },
    {
      "id": "alarm_1767931534_50",
      "threat_level": "CRITICAL",
      "vehicle_type": "T62",
      "confidence": 0.999998927116394,
      "threat_score": 0.9927496942281723,
      "timestamp": "2026-01-09T09:35:34.970873",
      "image_data": null,
      "acknowledged": false,
      "message": "CRITICAL threat detected: T62",
      "sar_validated": true
    },
    {
      "id": "alarm_1767934412_50",
      "threat_level": "CRITICAL",
      "vehicle_type": "T62",
      "confidence": 0.9999992847442627,
      "threat_score": 0.9927497961521149,
      "timestamp": "2026-01-09T10:23:32.784377",
      "image_data": null,
      "acknowledged": false,
      "message": "CRITICAL threat detected: T62",
      "sar_validated": true
    }
  ],
  "alarm_history": [
    {
      "id": "alarm_1764514534_0",
      "threat_level": "CRITICAL",
      "vehicle_type": "BMP2",
      "confidence": 0.9981315732002258,
      "threat_score": 0.9482249945402145,
      "timestamp": "2025-11-30T20:25:34.318113",
      "image_data": null,
      "acknowledged": true,
      "message": "CRITICAL threat detected: BMP2"
    },
    {
      "id": "alarm_1764514593_1",
      "threat_level": "CRITICAL",
      "vehicle_type": "2S1",
      "confidence": 0.9999594688415527,
      "threat_score": 0.949961495399475,
      "timestamp": "2025-11-30T20:26:33.903653",
      "image_data": null,
      "acknowledged": true,
      "message": "CRITICAL threat detected: 2S1"
    },
    {
      "id": "alarm_1764514723_2",
      "threat_level": "CRITICAL",
      "vehicle_type": "2S1",
      "confidence": 0.9999594688415527,
      "threat_score": 0.949961495399475,
      "timestamp": "2025-11-30T20:28:43.658270",
      "image_data": null,
      "acknowledged": false,
      "message": "CRITICAL threat detected: 2S1"
    },
    {
      "id": "alarm_1764577597_3",
      "threat_level": "CRITICAL",
      "vehicle_type": "2S1",
      "confidence": 0.9998249411582947,
      "threat_score": 0.9498336941003799,
      "timestamp": "2025-12-01T13:56:37.244194",
      "image_data": null,
      "acknowledged": false,
      "message": "CRITICAL threat detected: 2S1"
    },
    {
      "id": "alarm_1764578172_4",
      "threat_level": "CRITICAL",
      "vehicle_type": "2S1",
      "confidence": 0.9970923662185669,
      "threat_score": 0.9472377479076385,
      "timestamp": "2025-12-01T14:06:12.238505",
      "image_data": null,
      "acknowledged": false,
      "message": "CRITICAL threat detected: 2S1"
    },
    {
      "id": "alarm_1764578715_5",
      "threat_level": "CRITICAL",
      "vehicle_type": "2S1",
      "confidence": 0.9999594688415527,
      "threat_score": 0.949961495399475,
      "timestamp": "2025-12-01T14:15:15.894292",
      "image_data": null,
      "acknowledged": false,
      "message": "CRITICAL threat detected: 2S1"
    },
    {
      "id": "alarm_1764578899_6",
      "threat_level": "CRITICAL",
      "vehicle_type": "BMP2",
      "confidence": 0.9952045679092407,
      "threat_score": 0.9454443395137786,
      "timestamp": "2025-12-01T14:18:19.317163",
      "image_data": null,
      "acknowledged": false,
      "message": "CRITICAL threat detected: BMP2"
    },
    {
      "id": "alarm_1764578923_7",
      "threat_level": "CRITICAL",
      "vehicle_type": "ZSU_23_4",
      "confidence": 0.9999909400939941,
      "threat_score": 0.9499913930892944,
      "timestamp": "2025-12-01T14:18:43.431697",
      "image_data": null,
      "acknowledged": false,
      "message": "CRITICAL threat detected: ZSU_23_4"
    },
    {
      "id": "alarm_1764578969_8",
      "threat_level": "CRITICAL",
      "vehicle_type": "ZSU_23_4",
      "confidence": 0.9999980926513672,
      "threat_score": 0.9499981880187988,
      "timestamp": "2025-12-01T14:19:29.659689",
      "image_data": null,
      "acknowledged": false,
      "message": "CRITICAL threat detected: ZSU_23_4"
    },
    {
      "id": "alarm_1764579561_9",
      "threat_level": "CRITICAL",
      "vehicle_type": "ZSU_23_4",
      "confidence": 0.9999449253082275,
      "threat_score": 0.9499476790428161,
      "timestamp": "2025-12-01T14:29:21.571026",
      "image_data": null,
      "acknowledged": false,
      "message": "CRITICAL threat detected: ZSU_23_4"
    },
    {
      "id": "alarm_1764598735_10",
      "threat_level": "CRITICAL",
      "vehicle_type": "ZSU_23_4",
      "confidence": 0.9998701810836792,
      "threat_score": 0.9498766720294952,
      "timestamp": "2025-12-01T19:48:55.840873",
      "image_data": null,
      "acknowledged": false,
      "message": "CRITICAL threat detected: ZSU_23_4"
    },
    {
      "id": "alarm_1764645754_11",
      "threat_level": "CRITICAL",
      "vehicle_type": "ZSU_23_4",
      "confidence": 0.9999157190322876,
      "threat_score": 0.9499199330806731,
      "timestamp": "2025-12-02T08:52:34.853000",
      "image_data": null,
      "acknowledged": false,
      "message": "CRITICAL threat detected: ZSU_23_4"
    },
    {
      "id": "alarm_1764646423_12",
      "threat_level": "CRITICAL",
      "vehicle_type": "2S1",
      "confidence": 0.9998249411582947,
      "threat_score": 0.9498336941003799,
      "timestamp": "2025-12-02T09:03:43.637388",
      "image_data": null,
      "acknowledged": false,
      "message": "CRITICAL threat detected: 2S1"
    },
    {
      "id": "alarm_1764646478_13",
      "threat_level": "CRITICAL",
      "vehicle_type": "2S1",
      "confidence": 0.9998249411582947,
      "threat_score": 0.9498336941003799,
      "timestamp": "2025-12-02T09:04:38.152632",
      "image_data": null,
      "acknowledged": false,
      "message": "CRITICAL threat detected: 2S1"
    },
    {
      "id": "alarm_1764647003_14",
      "threat_level": "CRITICAL",
      "vehicle_type": "2S1",
      "confidence": 0.9998297691345215,
      "threat_score": 0.9498382806777954,
      "timestamp": "2025-12-02T09:13:23.208721",
      "image_data": null,
      "acknowledged": false,
      "message": "CRITICAL threat detected: 2S1"
    },
    {
      "id": "alarm_1764656951_15",
      "threat_level": "CRITICAL",
      "vehicle_type": "2S1",
      "confidence": 0.9998297691345215,
      "threat_score": 0.9498382806777954,
      "timestamp": "2025-12-02T11:59:11.862338",
      "image_data": null,
      "acknowledged": false,
      "message": "CRITICAL threat detected: 2S1"
    },
    {
      "id": "alarm_1764657487_16",
      "threat_level": "CRITICAL",
      "vehicle_type": "T62",
      "confidence": 0.998097836971283,
      "threat_score": 0.9481929451227188,
      "timestamp": "2025-12-02T12:08:07.464330",
      "image_data": null,
      "acknowledged": false,
      "message": "CRITICAL threat detected: T62"
    },
    {
      "id": "alarm_1764745345_17",
      "threat_level": "CRITICAL",
      "vehicle_type": "T62",
      "confidence": 0.9999983310699463,
      "threat_score": 0.949998414516449,
      "timestamp": "2025-12-03T12:32:25.195253",
      "image_data": null,
      "acknowledged": false,
      "message": "CRITICAL threat detected: T62"
    },
    {
      "id": "alarm_1765103558_18",
      "threat_level": "CRITICAL",
      "vehicle_type": "2S1",
      "confidence": 0.9943267703056335,
      "threat_score": 0.9446104317903519,
      "timestamp": "2025-12-07T16:02:38.912776",
      "image_data": null,
      "acknowledged": false,
      "message": "CRITICAL threat detected: 2S1"
    },
    {
      "id": "alarm_1765179538_19",
      "threat_level": "HIGH",
      "vehicle_type": "BMP2",
      "confidence": 0.9981315732002258,
      "threat_score": 0.8355515775680543,
      "timestamp": "2025-12-08T13:08:58.935587",
      "image_data": null,
      "acknowledged": false,
      "message": "HIGH threat detected: BMP2",
      "sar_validated": true
    },
    {
      "id": "alarm_1765179969_20",
      "threat_level": "CRITICAL",
      "vehicle_type": "T62",
      "confidence": 0.9999722242355347,
      "threat_score": 0.9927420839071275,
      "timestamp": "2025-12-08T13:16:09.166006",
      "image_data": null,
      "acknowledged": false,
      "message": "CRITICAL threat detected: T62",
      "sar_validated": true
    },
    {
      "id": "alarm_1765180041_21",
      "threat_level": "CRITICAL",
      "vehicle_type": "T72",
      "confidence": 0.9999910593032837,
      "threat_score": 0.9927474519014358,
      "timestamp": "2025-12-08T13:17:21.743200",
      "image_data": null,
      "acknowledged": false,
      "message": "CRITICAL threat detected: T72",
      "sar_validated": true
    },
    {
      "id": "alarm_1765182973_22",
      "threat_level": "CRITICAL",
      "vehicle_type": "T62",
      "confidence": 0.9998051524162292,
      "threat_score": 0.9926944684386253,
      "timestamp": "2025-12-08T14:06:13.630934",
      "image_data": null,
      "acknowledged": false,
      "message": "CRITICAL threat detected: T62",
      "sar_validated": true
    },
    {
      "id": "alarm_1765182996_23",
      "threat_level": "HIGH",
      "vehicle_type": "2S1",
      "confidence": 0.9996274709701538,
      "threat_score": 0.8359105930328369,
      "timestamp": "2025-12-08T14:06:36.763547",
      "image_data": null,
      "acknowledged": false,
      "message": "HIGH threat detected: 2S1",
      "sar_validated": true
    },
    {
      "id": "alarm_1765195107_24",
      "threat_level": "CRITICAL",
      "vehicle_type": "T72",
      "confidence": 0.9999982118606567,
      "threat_score": 0.992749490380287,
      "timestamp": "2025-12-08T17:28:27.521851",
      "image_data": null,
      "acknowledged": false,
      "message": "CRITICAL threat detected: T72",
      "sar_validated": true
    },
    {
      "id": "alarm_1765195205_25",
      "threat_level": "CRITICAL",
      "vehicle_type": "T72",
      "confidence": 0.9978808164596558,
      "threat_score": 0.9921460326910018,
      "timestamp": "2025-12-08T17:30:05.989103",
      "image_data": null,
      "acknowledged": false,
      "message": "CRITICAL threat detected: T72",
      "sar_validated": true
    },
    {
      "id": "alarm_1765205557_26",
      "threat_level": "HIGH",
      "vehicle_type": "BMP2",
      "confidence": 0.9981619715690613,
      "threat_score": 0.8355588731765748,
      "timestamp": "2025-12-08T20:22:37.789338",
      "image_data": null,
      "acknowledged": false,
      "message": "HIGH threat detected: BMP2",
      "sar_validated": true
    },
    {
      "id": "alarm_1765205660_27",
      "threat_level": "HIGH",
      "vehicle_type": "BMP2",
      "confidence": 0.9997324347496033,
      "threat_score": 0.8359357843399048,
      "timestamp": "2025-12-08T20:24:20.810754",
      "image_data": null,
      "acknowledged": false,
      "message": "HIGH threat detected: BMP2",
      "sar_validated": true
    },
    {
      "id": "alarm_1765206488_28",
      "threat_level": "HIGH",
      "vehicle_type": "ZSU_23_4",
      "confidence": 0.9999785423278809,
      "threat_score": 0.8359948501586913,
      "timestamp": "2025-12-08T20:38:08.584252",
      "image_data": null,
      "acknowledged": false,
      "message": "HIGH threat detected: ZSU_23_4",
      "sar_validated": true
    },
    {
      "id": "alarm_1765208515_29",
      "threat_level": "HIGH",
      "vehicle_type": "ZSU_23_4",
      "confidence": 0.9998701810836792,
      "threat_score": 0.835968843460083,
      "timestamp": "2025-12-08T21:11:55.549486",
      "image_data": null,
      "acknowledged": false,
      "message": "HIGH threat detected: ZSU_23_4",
      "sar_validated": true
    },
    {
      "id": "alarm_1765208535_30",
      "threat_level": "CRITICAL",
      "vehicle_type": "T72",
      "confidence": 0.9999910593032837,
      "threat_score": 0.9927474519014358,
      "timestamp": "2025-12-08T21:12:15.154767",
      "image_data": null,
      "acknowledged": false,
      "message": "CRITICAL threat detected: T72",
      "sar_validated": true
    },
    {
      "id": "alarm_1765208557_31",
      "threat_level": "HIGH",
      "vehicle_type": "2S1",
      "confidence": 0.9970923662185669,
      "threat_score": 0.8353021678924561,
      "timestamp": "2025-12-08T21:12:37.365905",
      "image_data": null,
      "acknowledged": false,
      "message": "HIGH threat detected: 2S1",
      "sar_validated": true
    },
    {
      "id": "alarm_1765263847_32",
      "threat_level": "HIGH",
      "vehicle_type": "2S1",
      "confidence": 0.9970923662185669,
      "threat_score": 0.8353021678924561,
      "timestamp": "2025-12-09T12:34:07.505324",
      "image_data": null,
      "acknowledged": false,
      "message": "HIGH threat detected: 2S1",
      "sar_validated": true
    },
    {
      "id": "alarm_1765285754_33",
      "threat_level": "HIGH",
      "vehicle_type": "2S1",
      "confidence": 0.9970923662185669,
      "threat_score": 0.8353021678924561,
      "timestamp": "2025-12-09T18:39:14.874440",
      "image_data": null,
      "acknowledged": false,
      "message": "HIGH threat detected: 2S1",
      "sar_validated": true
    },
    {
      "id": "alarm_1765285778_34",
      "threat_level": "CRITICAL",
      "vehicle_type": "T62",
      "confidence": 0.998097836971283,
      "threat_score": 0.9922078835368157,
      "timestamp": "2025-12-09T18:39:38.751802",
      "image_data": null,
      "acknowledged": false,
      "message": "CRITICAL threat detected: T62",
      "sar_validated": true
    },
    {
      "id": "alarm_1765287383_35",
      "threat_level": "CRITICAL",
      "vehicle_type": "T62",
      "confidence": 0.9994402527809143,
      "threat_score": 0.9925904720425607,
      "timestamp": "2025-12-09T19:06:23.897856",
      "image_data": null,
      "acknowledged": false,
      "message": "CRITICAL threat detected: T62",
      "sar_validated": true
    },
    {
      "id": "alarm_1765287404_36",
      "threat_level": "HIGH",
      "vehicle_type": "2S1",
      "confidence": 0.9998249411582947,
      "threat_score": 0.8359579858779909,
      "timestamp": "2025-12-09T19:06:44.934951",
      "image_data": null,
      "acknowledged": false,
      "message": "HIGH threat detected: 2S1",
      "sar_validated": true
    },
    {
      "id": "alarm_1765288370_37",
      "threat_level": "HIGH",
      "vehicle_type": "2S1",
      "confidence": 0.9970923662185669,
      "threat_score": 0.8353021678924561,
      "timestamp": "2025-12-09T19:22:50.476309",
      "image_data": null,
      "acknowledged": false,
      "message": "HIGH threat detected: 2S1",
      "sar_validated": true
    },
    {
      "id": "alarm_1765288389_38",
      "threat_level": "HIGH",
      "vehicle_type": "2S1",
      "confidence": 0.9970923662185669,
      "threat_score": 0.8353021678924561,
      "timestamp": "2025-12-09T19:23:09.617210",
      "image_data": null,
      "acknowledged": false,
      "message": "HIGH threat detected: 2S1",
      "sar_validated": true
    },
    {
      "id": "alarm_1765288554_39",
      "threat_level": "HIGH",
      "vehicle_type": "2S1",
      "confidence": 0.9970923662185669,
      "threat_score": 0.8353021678924561,
      "timestamp": "2025-12-09T19:25:54.295995",
      "image_data": null,
      "acknowledged": false,
      "message": "HIGH threat detected: 2S1",
      "sar_validated": true
    },
    {
      "id": "alarm_1765339287_40",
      "threat_level": "CRITICAL",
      "vehicle_type": "T62",
      "confidence": 0.9997790455818176,
      "threat_score": 0.992687027990818,
      "timestamp": "2025-12-10T09:31:27.071530",
      "image_data": null,
      "acknowledged": false,
      "message": "CRITICAL threat detected: T62",
      "sar_validated": true
    },
    {
      "id": "alarm_1765339642_41",
      "threat_level": "HIGH",
      "vehicle_type": "BMP2",
      "confidence": 0.9416980147361755,
      "threat_score": 0.8220075235366822,
      "timestamp": "2025-12-10T09:37:22.971361",
      "image_data": null,
      "acknowledged": false,
      "message": "HIGH threat detected: BMP2",
      "sar_validated": true
    },
    {
      "id": "alarm_1765340037_42",
      "threat_level": "CRITICAL",
      "vehicle_type": "T62",
      "confidence": 0.9997790455818176,
      "threat_score": 0.992687027990818,
      "timestamp": "2025-12-10T09:43:57.805166",
      "image_data": null,
      "acknowledged": false,
      "message": "CRITICAL threat detected: T62",
      "sar_validated": true
    },
    {
      "id": "alarm_1765340852_43",
      "threat_level": "HIGH",
      "vehicle_type": "BMP2",
      "confidence": 0.9959074258804321,
      "threat_score": 0.8350177822113038,
      "timestamp": "2025-12-10T09:57:32.814156",
      "image_data": null,
      "acknowledged": false,
      "message": "HIGH threat detected: BMP2",
      "sar_validated": true
    },
    {
      "id": "alarm_1765340894_44",
      "threat_level": "CRITICAL",
      "vehicle_type": "T62",
      "confidence": 0.9999992847442627,
      "threat_score": 0.9927497961521149,
      "timestamp": "2025-12-10T09:58:14.588937",
      "image_data": null,
      "acknowledged": false,
      "message": "CRITICAL threat detected: T62",
      "sar_validated": true
    },
    {
      "id": "alarm_1765341878_45",
      "threat_level": "CRITICAL",
      "vehicle_type": "T72",
      "confidence": 0.9855168461799622,
      "threat_score": 0.9886223011612892,
      "timestamp": "2025-12-10T10:14:38.404883",
      "image_data": null,
      "acknowledged": false,
      "message": "CRITICAL threat detected: T72",
      "sar_validated": true
    },
    {
      "id": "alarm_1765345538_46",
      "threat_level": "CRITICAL",
      "vehicle_type": "T62",
      "confidence": 0.9999767541885376,
      "threat_score": 0.9927433749437331,
      "timestamp": "2025-12-10T11:15:38.961311",
      "image_data": null,
      "acknowledged": false,
      "message": "CRITICAL threat detected: T62",
      "sar_validated": true
    },
    {
      "id": "alarm_1765346843_47",
      "threat_level": "CRITICAL",
      "vehicle_type": "T72",
      "confidence": 0.9855168461799622,
      "threat_score": 0.9886223011612892,
      "timestamp": "2025-12-10T11:37:23.875880",
      "image_data": null,
      "acknowledged": false,
      "message": "CRITICAL threat detected: T72",
      "sar_validated": true
    },
    {
      "id": "alarm_1765347810_48",
      "threat_level": "CRITICAL",
      "vehicle_type": "T62",
      "confidence": 0.9999992847442627,
      "threat_score": 0.9927497961521149,
      "timestamp": "2025-12-10T11:53:30.544161",
      "image_data": null,
      "acknowledged": false,
      "message": "CRITICAL threat detected: T62",
      "sar_validated": true
    },
    {
      "id": "alarm_1765347898_49",
      "threat_level": "CRITICAL",
      "vehicle_type": "T62",
      "confidence": 0.9999992847442627,
      "threat_score": 0.9927497961521149,
      "timestamp": "2025-12-10T11:54:58.200921",
      "image_data": null,
      "acknowledged": false,
      "message": "CRITICAL threat detected: T62",
      "sar_validated": true
    },
    {
      "id": "alarm_1765348061_50",
      "threat_level": "CRITICAL",
      "vehicle_type": "T62",
      "confidence": 0.9999151229858398,
      "threat_score": 0.9927258100509643,
      "timestamp": "2025-12-10T11:57:41.468359",
      "image_data": null,
      "acknowledged": false,
      "message": "CRITICAL threat detected: T62",
      "sar_validated": true
    },
    {
      "id": "alarm_1765348300_50",
      "threat_level": "CRITICAL",
      "vehicle_type": "T62",
      "confidence": 0.9999992847442627,
      "threat_score": 0.9927497961521149,
      "timestamp": "2025-12-10T12:01:40.926117",
      "image_data": null,
      "acknowledged": false,
      "message": "CRITICAL threat detected: T62",
      "sar_validated": true
    },
    {
      "id": "alarm_1765348458_50",
      "threat_level": "CRITICAL",
      "vehicle_type": "T62",
      "confidence": 0.9999151229858398,
      "threat_score": 0.9927258100509643,
      "timestamp": "2025-12-10T12:04:18.036912",
      "image_data": null,
      "acknowledged": false,
      "message": "CRITICAL threat detected: T62",
      "sar_validated": true
    },
    {
      "id": "alarm_1765349496_50",
      "threat_level": "CRITICAL",
      "vehicle_type": "T62",
      "confidence": 0.9994136095046997,
      "threat_score": 0.9925828787088394,
      "timestamp": "2025-12-10T12:21:36.670358",
      "image_data": null,
      "acknowledged": false,
      "message": "CRITICAL threat detected: T62",
      "sar_validated": true
    },
    {
      "id": "alarm_1765350975_50",
      "threat_level": "CRITICAL",
      "vehicle_type": "T62",
      "confidence": 0.9999151229858398,
      "threat_score": 0.9927258100509643,
      "timestamp": "2025-12-10T12:46:15.130478",
      "image_data": null,
      "acknowledged": false,
      "message": "CRITICAL threat detected: T62",
      "sar_validated": true
    },
    {
      "id": "alarm_1765357716_50",
      "threat_level": "CRITICAL",
      "vehicle_type": "T62",
      "confidence": 0.9999992847442627,
      "threat_score": 0.9927497961521149,
      "timestamp": "2025-12-10T14:38:36.079320",
      "image_data": null,
      "acknowledged": false,
      "message": "CRITICAL threat detected: T62",
      "sar_validated": true
    },
    {
      "id": "alarm_1765357830_50",
      "threat_level": "HIGH",
      "vehicle_type": "2S1",
      "confidence": 0.9995386600494385,
      "threat_score": 0.8358892784118652,
      "timestamp": "2025-12-10T14:40:30.252075",
      "image_data": null,
      "acknowledged": false,
      "message": "HIGH threat detected: 2S1",
      "sar_validated": true
    },
    {
      "id": "alarm_1765434307_50",
      "threat_level": "HIGH",
      "vehicle_type": "2S1",
      "confidence": 0.9965943694114685,
      "threat_score": 0.8351826486587526,
      "timestamp": "2025-12-11T11:55:07.997353",
      "image_data": null,
      "acknowledged": false,
      "message": "HIGH threat detected: 2S1",
      "sar_validated": true
    },
    {
      "id": "alarm_1765434330_50",
      "threat_level": "CRITICAL",
      "vehicle_type": "T62",
      "confidence": 0.999998927116394,
      "threat_score": 0.9927496942281723,
      "timestamp": "2025-12-11T11:55:30.180148",
      "image_data": null,
      "acknowledged": false,
      "message": "CRITICAL threat detected: T62",
      "sar_validated": true
    },
    {
      "id": "alarm_1765434521_50",
      "threat_level": "CRITICAL",
      "vehicle_type": "T62",
      "confidence": 0.999998927116394,
      "threat_score": 0.9927496942281723,
      "timestamp": "2025-12-11T11:58:41.749334",
      "image_data": null,
      "acknowledged": false,
      "message": "CRITICAL threat detected: T62",
      "sar_validated": true
    },
    {
      "id": "alarm_1765468527_50",
      "threat_level": "CRITICAL",
      "vehicle_type": "T62",
      "confidence": 0.9999151229858398,
      "threat_score": 0.9927258100509643,
      "timestamp": "2025-12-11T21:25:27.485671",
      "image_data": null,
      "acknowledged": false,
      "message": "CRITICAL threat detected: T62",
      "sar_validated": true
    },
    {
      "id": "alarm_1767150869_50",
      "threat_level": "CRITICAL",
      "vehicle_type": "T62",
      "confidence": 0.9999992847442627,
      "threat_score": 0.9927497961521149,
      "timestamp": "2025-12-31T08:44:29.536619",
      "image_data": null,
      "acknowledged": false,
      "message": "CRITICAL threat detected: T62",
      "sar_validated": true
    },
    {
      "id": "alarm_1767151012_50",
      "threat_level": "CRITICAL",
      "vehicle_type": "T62",
      "confidence": 0.999998927116394,
      "threat_score": 0.9927496942281723,
      "timestamp": "2025-12-31T08:46:52.043114",
      "image_data": null,
      "acknowledged": false,
      "message": "CRITICAL threat detected: T62",
      "sar_validated": true
    },
    {
      "id": "alarm_1767434582_50",
      "threat_level": "CRITICAL",
      "vehicle_type": "T62",
      "confidence": 0.9999151229858398,
      "threat_score": 0.9927258100509643,
      "timestamp": "2026-01-03T15:33:02.988362",
      "image_data": null,
      "acknowledged": false,
      "message": "CRITICAL threat detected: T62",
      "sar_validated": true
    },
    {
      "id": "alarm_1767863547_50",
      "threat_level": "CRITICAL",
      "vehicle_type": "T62",
      "confidence": 0.9999992847442627,
      "threat_score": 0.9927497961521149,
      "timestamp": "2026-01-08T14:42:27.734685",
      "image_data": null,
      "acknowledged": false,
      "message": "CRITICAL threat detected: T62",
      "sar_validated": true
    },
    {
      "id": "alarm_1767931518_50",
      "threat_level": "CRITICAL",
      "vehicle_type": "T62",
      "confidence": 0.999998927116394,
      "threat_score": 0.9927496942281723,
      "timestamp": "2026-01-09T09:35:18.552258",
      "image_data": null,
      "acknowledged": false,
      "message": "CRITICAL threat detected: T62",
      "sar_validated": true
    },
    {
      "id": "alarm_1767931534_50",
      "threat_level": "CRITICAL",
      "vehicle_type": "T62",
      "confidence": 0.999998927116394,
      "threat_score": 0.9927496942281723,
      "timestamp": "2026-01-09T09:35:34.970873",
      "image_data": null,
      "acknowledged": false,
      "message": "CRITICAL threat detected: T62",
      "sar_validated": true
    },
    {
      "id": "alarm_1767934412_50",
      "threat_level": "CRITICAL",
      "vehicle_type": "T62",
      "confidence": 0.9999992847442627,
      "threat_score": 0.9927497961521149,
      "timestamp": "2026-01-09T10:23:32.784377",
      "image_data": null,
      "acknowledged": false,
      "message": "CRITICAL threat detected: T62",
      "sar_validated": true
    }
  ]
}